utt_project_summary/__init__.py
utt/plugins/project_summary.py
utt_project_summary-0.1.0.dist-info/METADATA
utt_project_summary-0.1.0.dist-info/WHEEL
utt_project_summary-0.1.0.dist-info/licenses/LICENSE
utt_project_summary-0.1.0.dist-info/RECORD
