Metadata-Version: 2.4
Name: utt-project-summary
Version: 0.1.0
Summary: A utt plugin to show projects sorted by time spent
Project-URL: Homepage, https://github.com/loganthomas/utt-project-summary
Project-URL: Repository, https://github.com/loganthomas/utt-project-summary
Project-URL: Issues, https://github.com/loganthomas/utt-project-summary/issues
Author-email: Logan Thomas <logan@datacentriq.net>
License-Expression: GPL-3.0-only
License-File: LICENSE
Keywords: plugin,productivity,project-summary,time-tracking,utt
Classifier: Development Status :: 4 - Beta
Classifier: Environment :: Console
Classifier: Intended Audience :: End Users/Desktop
Classifier: Operating System :: OS Independent
Classifier: Programming Language :: Python :: 3
Classifier: Programming Language :: Python :: 3.10
Classifier: Programming Language :: Python :: 3.11
Classifier: Programming Language :: Python :: 3.12
Classifier: Programming Language :: Python :: 3.13
Classifier: Topic :: Office/Business :: Scheduling
Classifier: Topic :: Utilities
Requires-Python: >=3.10
Requires-Dist: utt>=1.0
Provides-Extra: dev
Requires-Dist: pre-commit>=3.0; extra == 'dev'
Requires-Dist: pytest-cov>=4.0; extra == 'dev'
Requires-Dist: pytest>=7.0; extra == 'dev'
Requires-Dist: pytz>=2024.1; extra == 'dev'
Requires-Dist: ruff>=0.4; extra == 'dev'
Requires-Dist: ty>=0.0.1a1; extra == 'dev'
